{
  "homeKey": "Home",
  "onLiveKey": "On Live",
  "offlineKey": "Offline",
  "championSelectKey": "Champion Select",
  "statisticsKey": "Statistics",
  "notebookKey": "Notebook",
  "joinBattleKey": "Join the Battle",
  "lnkRegisterKey": "Register",
  "lnkForgotKey": "Forgot your password?",
  "socialMediaKey": "Or Log in with social media",
  "getStartedKey": "GET STARTED",
  "onLiveToolKey": "On live tool",
  "onLiveToolTextKey": "Search your summoner to get all the information you need of your current game",
  "offlineToolKey": "Offline tool",
  "offlineToolTextKey": "Search your summoner to find all the information about your account and ranking history",
  "championSelectToolKey": "Champion Select tool",
  "championSelectToolTextKey": "Use the Champion Select tool to pick the perfect champion for each situation",
  "statisticsToolKey": "Statistics",
  "statisticsToolTextKey": "Do your own analisys using this giant tool based on the server statistics.",
  "onLiveTitleKey": "On Live Tool",
  "onLiveDescKey": "You can search the actual game of any Summoner you want obtaining a lof of information just putting the name of the summoner on the text box.",
  "aboutKey": "About Smart Lol",
  "contactKey": "Contact Us",
  "privacyKey": "Privacy Policy",
  "faqKey": "FAQ",
  "txtUsernameKey": "Username or email",
  "txtPasswordKey": "Password",
  "btnLoginKey": "Log In",
  "languajeBtn": "English"
}